microwinebar/__init__.py
microwinebar/allsamples.py
microwinebar/bracken2microwinebar.py
microwinebar/data.py
microwinebar/displaying.py
microwinebar/displaying2.py
microwinebar/general_functions.py
microwinebar/metaphlan2microwinebar.py
microwinebar/mgmapper2microwinebar.py
microwinebar/microwinebar.py
microwinebar/popupwindow.py
microwinebar/popupwindow_matplotlib.py
microwinebar-0.0.1.dist-info/LICENSE
microwinebar-0.0.1.dist-info/METADATA
microwinebar-0.0.1.dist-info/WHEEL
microwinebar-0.0.1.dist-info/entry_points.txt
microwinebar-0.0.1.dist-info/top_level.txt
microwinebar-0.0.1.dist-info/RECORD
