Metadata-Version: 2.1
Name: microwinebar
Version: 0.0.1
Summary: MicroWineBar
Home-page: https://github.com/klincke/microwinebar
Author: klincke
Author-email: franziska.klincke@bio.ku.dk
License: UNKNOWN
Platform: UNKNOWN
Classifier: Programming Language :: Python :: 3
Classifier: Programming Language :: Python :: 3.6
Classifier: Programming Language :: Python :: 3.7
Classifier: License :: OSI Approved :: MIT License
Classifier: Operating System :: MacOS
Classifier: Operating System :: POSIX
Classifier: Operating System :: Unix
Classifier: Intended Audience :: Science/Research
Classifier: Topic :: Scientific/Engineering :: Bio-Informatics
Requires-Dist: matplotlib (==2.2.3)
Requires-Dist: openpyxl (==2.6.0)
Requires-Dist: numpy (==1.16.4)
Requires-Dist: pandas (==0.24.2)
Requires-Dist: scipy (==1.3.0)
Requires-Dist: scikit-learn (==0.21.2)
Requires-Dist: scikit-bio (==0.5.5)
Requires-Dist: wikipedia (==1.4.0)
Requires-Dist: Pmw (==2.0.1)
Requires-Dist: seaborn
